panel_server/__init__.py
panel_server/__version.py
panel_server/_version.py
panel_server/icons/logo.svg
panel_server/tests/test_basic.py
jupyter_panel_proxy-0.2.0.dist-info/METADATA
jupyter_panel_proxy-0.2.0.dist-info/WHEEL
jupyter_panel_proxy-0.2.0.dist-info/entry_points.txt
jupyter_panel_proxy-0.2.0.dist-info/licenses/LICENSE
jupyter_panel_proxy-0.2.0.dist-info/RECORD
