Metadata-Version: 2.4
Name: jupyter-panel-proxy
Version: 0.2.0
Summary: Jupyter Server Proxy for Panel applications
Project-URL: Homepage, https://github.com/holoviz-dev/jupyter-panel-proxy
Project-URL: Source, https://github.com/holoviz-dev/jupyter-panel-proxy
Project-URL: BugTracker, https://github.com/holoviz-dev/jupyter-panel-proxy/issues
Project-URL: Documentation, https://github.com/holoviz/jupyter-panel-proxy/blob/main/README.md
Project-URL: Source Code, https://github.com/holoviz/jupyter-panel-proxy
Author-email: Julia Signell <developers@holoviz.org>
Maintainer-email: HoloViz developers <developers@pyviz.org>
License-Expression: BSD-3-Clause
License-File: LICENSE
Classifier: Development Status :: 5 - Production/Stable
Classifier: Intended Audience :: Developers
Classifier: Intended Audience :: Science/Research
Classifier: License :: OSI Approved :: BSD License
Classifier: Natural Language :: English
Classifier: Operating System :: OS Independent
Classifier: Programming Language :: Python
Classifier: Programming Language :: Python :: 3.9
Classifier: Programming Language :: Python :: 3.10
Classifier: Programming Language :: Python :: 3.11
Classifier: Programming Language :: Python :: 3.12
Classifier: Programming Language :: Python :: 3.13
Classifier: Topic :: Scientific/Engineering
Classifier: Topic :: Software Development :: Libraries
Requires-Python: >=3.9
Requires-Dist: jupyter-server-proxy
Requires-Dist: panel>=0.11
Requires-Dist: pyyaml
Provides-Extra: tests
Requires-Dist: pytest; extra == 'tests'
